odoo/addons/stock_landed_costs_purchase_auto/README.rst
odoo/addons/stock_landed_costs_purchase_auto/__init__.py
odoo/addons/stock_landed_costs_purchase_auto/__manifest__.py
odoo/addons/stock_landed_costs_purchase_auto/i18n/es.po
odoo/addons/stock_landed_costs_purchase_auto/i18n/fr.po
odoo/addons/stock_landed_costs_purchase_auto/i18n/it.po
odoo/addons/stock_landed_costs_purchase_auto/i18n/stock_landed_costs_purchase_auto.pot
odoo/addons/stock_landed_costs_purchase_auto/models/__init__.py
odoo/addons/stock_landed_costs_purchase_auto/models/purchase_order.py
odoo/addons/stock_landed_costs_purchase_auto/models/stock_landed_cost.py
odoo/addons/stock_landed_costs_purchase_auto/models/stock_picking.py
odoo/addons/stock_landed_costs_purchase_auto/readme/CONTRIBUTORS.md
odoo/addons/stock_landed_costs_purchase_auto/readme/DESCRIPTION.md
odoo/addons/stock_landed_costs_purchase_auto/readme/USAGE.md
odoo/addons/stock_landed_costs_purchase_auto/static/description/icon.png
odoo/addons/stock_landed_costs_purchase_auto/static/description/index.html
odoo/addons/stock_landed_costs_purchase_auto/tests/__init__.py
odoo/addons/stock_landed_costs_purchase_auto/tests/common.py
odoo/addons/stock_landed_costs_purchase_auto/tests/test_purchase_order.py
odoo/addons/stock_landed_costs_purchase_auto/views/purchase_order_view.xml
odoo/addons/stock_landed_costs_purchase_auto/views/stock_landed_cost_view.xml
odoo_addon_stock_landed_costs_purchase_auto-18.0.1.0.0.2.dist-info/METADATA
odoo_addon_stock_landed_costs_purchase_auto-18.0.1.0.0.2.dist-info/WHEEL
odoo_addon_stock_landed_costs_purchase_auto-18.0.1.0.0.2.dist-info/top_level.txt
odoo_addon_stock_landed_costs_purchase_auto-18.0.1.0.0.2.dist-info/RECORD
